{"file":"default-D7VaM3Uo.js","mappings":";;;;;;;;;;;;;;;;;;;AAAA,QAAA,OAAAA,eAAAC,WAAA,EAAA,OAK0B,YAAI,MAAA,CAAA,CAAA,6FAAA;AAL9B,QAAAC,mBAKmD,qBAAA,EAAA,IAAA,IAAA,GAAA;AAAA,IALnD,SAAAC,QAAA,CAAA,GAAAC,QAAAC,UAAA,aAAA;AAAA,UAAAD,QAAA;;;AAAA,eAAA;AAAA;;;KAAA;AAAA;EAAA,GAAA,OAAA,CAAA;AAAA,QAAA,2BAAA;AAAA,QAAAF,mBAMwD,qBAAA,EAAA,IAAA,WAAA,GAAA;AAAA,IANxD,SAAAC,QAAA,CAAA,GAAAC,QAAAC,UAAA,aAAA;AAAA,UAAAD,QAAA;;;AAAA,eAAA;AAAA;;;KAAA;AAAA;EAAA,GAAA,OAAA,CAAA;AAAA,QAAA,2BAAA;AAAA,QAAAF,mBAOwD,qBAAA,EAAA,IAAA,WAAA,GAAA;AAAA,IAPxD,SAAAC,QAAA,CAAA,GAAAC,QAAAC,UAAA,aAAA;AAAA,UAAAD,QAAA;;;AAAA,eAAA;AAAA;;;KAAA;AAAA;EAAA,GAAA,OAAA,CAAA;AAAA,QAAA,2BAAA;AAAA,QAAAF,mBAQ0D,qBAAA,EAAA,IAAA,YAAA,GAAA;AAAA,IAR1D,SAAAC,QAAA,CAAA,GAAAC,QAAAC,UAAA,aAAA;AAAA,UAAAD,QAAA;;;AAAA,eAAA;AAAA;;;KAAA;AAAA;EAAA,GAAA,OAAA,CAAA;AAAA,QAAA,wCAAA;AAAA,QAAAF,mBAAA,qBAAA,MAAA,MAAA,OAAA,CAAA;;;;;;;;;;","names":["_ssrRenderAttrs","_mergeProps","_ssrRenderComponent","_withCtx","_push","_parent"],"sources":["../../../../layouts/default.vue"],"sourcesContent":["<template>\n    <div class=\"layout\">\n      <!-- Menu -->\n      <nav class=\"menu\">\n        <ul>\n          <li><NuxtLink to=\"/\">Ana sayfa</NuxtLink></li>\n          <li><NuxtLink to=\"/araclar\">Araclar</NuxtLink></li>\n          <li><NuxtLink to=\"/urunler\">Ürünler</NuxtLink></li>\n          <li><NuxtLink to=\"/satislar\">Satislar</NuxtLink></li>\n        </ul>\n      </nav>\n  \n      <!-- Page Content -->\n      <main>\n        <NuxtPage />\n      </main>\n  \n      <!-- Footer -->\n      <footer>\n        <p>&copy; 2024</p>\n      </footer>\n    </div>\n  </template>\n  \n  <style scoped>\n  .layout {\n    display: flex;\n    flex-direction: column;\n    height: 100vh;\n  }\n  \n  .menu {\n    display: flex;\n    flex-direction: row;\n    justify-content: flex-start;\n    background-color: #333;\n    padding: 15px;\n  }\n  \n  .menu ul {\n    list-style-type: none;\n    margin: 0;\n    padding: 0;\n    display: flex;\n    gap: 15px;\n  }\n  \n  .menu ul li {\n    display: inline;\n  }\n  \n  .menu ul li a {\n    color: white;\n    text-decoration: none;\n    font-weight: bold;\n  }\n  \n  main {\n    flex: 1;\n    padding: 20px;\n    background-color: #f5f5f5;\n  }\n  \n  footer {\n    background-color: #333;\n    color: white;\n    text-align: center;\n    padding: 10px 0;\n  }\n  </style>\n  "],"version":3}